{
  "0": [
    {"Date": "",
      "rank": "solemnity",
      "key": "body_and_blood",
      "Title": "The Most Holy Body and Blood of Christ",
      "dateNote": "Sunday after the Most Holy Trinity"}
  ],
  "1": [
    {
      "Date": "",
      "rank": "solemnity",
      "key": "epiphany",
      "Title": "The Epiphany of the Lord",
      "dateNote": "Sunday between Jan 2 and 8"
    },
    {
      "Date": "4",
      "rank": "memorial",
      "key": "elizabeth_ann_seton",
      "Title": "Saint Elizabeth Ann Seton, Religious"
    },
    {
      "Date": "5",
      "rank": "memorial",
      "key": "neumann",
      "Title": "Saint John Neumann, Bishop"
    },
    {
      "Date": "6",
      "key": "bessette",
      "Title": "Saint André Bessette, Religious"
    },
    {
      "Date": "22",
      "rank": "memorial",
      "altDateSunday": "23",
      "key": "unborn",
      "Title": "Day of Prayer for the Legal Protection of Unborn Children"
    },
    {
      "Date": "23",
      "key": "vincent_marianne",
      "Title": "Saint Vincent, Deacon and Martyr; Saint Marianne Cope, Virgin"
    }
  ],
  "3": [
    {
      "Date": "3",
      "key": "katharine_drexel",
      "Title": "Saint Katharine Drexel, Virgin"
    }
  ],
  "4": [
    {
      "Date": "10",
      "key": "damien",
      "Title": "Saint Damien de Veuster, Priest"
    },
    {
      "Date": "15",
      "key": "isidore",
      "Title": "Saint Isidore"
    }
  ],
  "7": [
    {
      "Date": "1",
      "key": "junipero_serra",
      "Title": "Saint Junípero Serra, Priest"
    },
    {
      "Date": "4",
      "key": "indepencence_day",
      "Title": "Independence Day"
    },
    {
      "Date": "5",
      "key": "elizabeth_portugal",
      "Title": "Saint Elizabeth of Portugal"
    },
    {
      "Date": "14",
      "key": "kateri",
      "rank": "memorial",
      "Title": "Saint Kateri Tekakwitha, Virgin"
    },
    {
      "Date": "18",
      "key": "camillus",
      "Title": "Saint Camillus de Lellis, Priest"
    }
  ],
  "9": [
    {
      "Date": "9",
      "rank": "memorial",
      "key": "peter_claver",
      "Title": "Saint Peter Claver, Priest"
    }
  ],
  "10": [
    {
      "Date": "5",
      "key": "francis_xavier",
      "Title": "Blessed Francis Xavier Seelos, Priest"
    },
    {
      "Date": "6",
      "key": "marie_durocher",
      "Title": "Blessed Marie Rose Durocher, Virgin"
    },
    {
      "Date": "19",
      "key": "john_isaac",
      "rank": "memorial",
      "Title": "Saints John de Brébeuf and Isaac Jogues, Priests, and Companions, Martyrs"
    },
    {
      "Date": "20",
      "key": "paul_cross",
      "Title": "Saint Paul of the Cross, Priest"
    }
  ],
  "11": [
    {
      "Date": "13",
      "key": "cabrini",
      "rank": "memorial",
      "Title": "Saint Frances Xavier Cabrini, Virgin"
    },
    {
      "Date": "18",
      "key": "rose_duchesne",
      "Title": "Saint Rose Philippine Duchesne, Virgin"
    },
    {
      "Date": "23",
      "key": "miguel_pro",
      "Title": "Blessed Miguel Agustín Pro, Priest and Martyr"
    },
    {
      "Date": "",
      "key": "thanksgiving",
      "Title": "Thanksgiving Day"
    }
  ],
  "12": [
    {
      "Date": "8",
      "key": "immaculate_conception",
      "rank": "solemnity",
      "Title": "Immaculate Conception of the Blessed Virgin Mary, Patronal Feastday of the United States of America"
    },
    {
      "Date": "12",
      "key": "lady_guadalupe",
      "rank": "feast",
      "Title": "Our Lady of Guadalupe"
    }
  ]
}